{
  "fetched_at": "2026-06-12T19:27:08.972109+00:00",
  "sp500": {
    "price": 7429.92,
    "change_pct": 2.24,
    "label": "S&P 500"
  },
  "nasdaq": {
    "price": 25889.08,
    "change_pct": 2.86,
    "label": "Nasdaq"
  },
  "dow": {
    "price": 51231.68,
    "change_pct": 2.63,
    "label": "Dow"
  },
  "vix": {
    "price": 18.29,
    "change_pct": -5.92,
    "label": "VIX"
  },
  "btc": {
    "price": 63749.05,
    "change_pct": 0.3,
    "label": "BTC"
  },
  "watchlist": {
    "NVDA": {
      "price": 204.91,
      "change_pct": 0.02
    },
    "MRVL": {
      "price": 285.62,
      "change_pct": 1.75
    },
    "TSLA": {
      "price": 403.22,
      "change_pct": 1.02
    },
    "MSTR": {
      "price": 123.71,
      "change_pct": 2.96
    },
    "GOOGL": {
      "price": 359.84,
      "change_pct": 0.58
    },
    "AMD": {
      "price": 514.84,
      "change_pct": 5.4
    },
    "META": {
      "price": 567.28,
      "change_pct": -0.2
    },
    "MSFT": {
      "price": 389.5,
      "change_pct": -0.22
    },
    "AMZN": {
      "price": 237.69,
      "change_pct": -1.58
    },
    "AVGO": {
      "price": 381.52,
      "change_pct": -1.05
    }
  },
  "trending": [
    {
      "ticker": "NVDA",
      "mentions": 94,
      "surge_pct": 0
    },
    {
      "ticker": "TSLA",
      "mentions": 29,
      "surge_pct": 0
    },
    {
      "ticker": "GOOGL",
      "mentions": 19,
      "surge_pct": 0
    },
    {
      "ticker": "META",
      "mentions": 10,
      "surge_pct": 0
    },
    {
      "ticker": "AMZN",
      "mentions": 8,
      "surge_pct": 0
    },
    {
      "ticker": "MSFT",
      "mentions": 7,
      "surge_pct": 0
    },
    {
      "ticker": "INTC",
      "mentions": 6,
      "surge_pct": 0
    },
    {
      "ticker": "MRVL",
      "mentions": 5,
      "surge_pct": 0
    },
    {
      "ticker": "MU",
      "mentions": 4,
      "surge_pct": 0
    },
    {
      "ticker": "AMD",
      "mentions": 4,
      "surge_pct": 0
    }
  ],
  "mood_score": 84,
  "mood": "bullish",
  "mood_summary": "S&P +2.24% · Nasdaq +2.86%"
}