{
  "fetched_at": "2026-04-28T05:23:40.159531+00:00",
  "kospi": {
    "price": 6655.87,
    "change_pct": 0.62,
    "label": "KOSPI"
  },
  "kosdaq": {
    "price": 1216.75,
    "change_pct": -0.77,
    "label": "KOSDAQ"
  },
  "kospi200": {
    "price": 1001.61,
    "change_pct": 0.63,
    "label": "KPI200"
  },
  "watchlist": {
    "005930": {
      "price": 222500.0,
      "change_pct": -0.89,
      "name": "삼성전자",
      "code": "005930"
    },
    "000660": {
      "price": 1309000.0,
      "change_pct": 1.32,
      "name": "SK하이닉스",
      "code": "000660"
    },
    "373220": {
      "price": 466000.0,
      "change_pct": 0.43,
      "name": "LG에너지솔루션",
      "code": "373220"
    },
    "005380": {
      "price": 557000.0,
      "change_pct": 6.3,
      "name": "현대차",
      "code": "005380"
    },
    "035420": {
      "price": 219000.0,
      "change_pct": 1.86,
      "name": "NAVER",
      "code": "035420"
    },
    "035720": {
      "price": 48550.0,
      "change_pct": 0.21,
      "name": "카카오",
      "code": "035720"
    },
    "207940": {
      "price": 1506000.0,
      "change_pct": -0.2,
      "name": "삼성바이오로직스",
      "code": "207940"
    },
    "005490": {
      "price": 462000.0,
      "change_pct": 10.66,
      "name": "포스코홀딩스",
      "code": "005490"
    },
    "051910": {
      "price": 393500.0,
      "change_pct": 3.69,
      "name": "LG화학",
      "code": "051910"
    },
    "247540": {
      "price": 211500.0,
      "change_pct": 1.93,
      "name": "에코프로비엠",
      "code": "247540"
    }
  },
  "trending": [
    {
      "ticker": "005930",
      "name": "삼성전자",
      "mentions": 6,
      "surge_pct": 0
    },
    {
      "ticker": "000660",
      "name": "SK하이닉스",
      "mentions": 4,
      "surge_pct": 0
    },
    {
      "ticker": "005380",
      "name": "현대차",
      "mentions": 3,
      "surge_pct": 0
    },
    {
      "ticker": "042660",
      "name": "한화오션",
      "mentions": 3,
      "surge_pct": 0
    },
    {
      "ticker": "035420",
      "name": "네이버",
      "mentions": 3,
      "surge_pct": 0
    },
    {
      "ticker": "041510",
      "name": "SM",
      "mentions": 2,
      "surge_pct": 0
    },
    {
      "ticker": "006400",
      "name": "삼성SDI",
      "mentions": 1,
      "surge_pct": 0
    },
    {
      "ticker": "107600",
      "name": "새빗켐",
      "mentions": 1,
      "surge_pct": 0
    },
    {
      "ticker": "005870",
      "name": "휴니드테크놀러지스",
      "mentions": 1,
      "surge_pct": 0
    },
    {
      "ticker": "007340",
      "name": "DN오토모티브",
      "mentions": 1,
      "surge_pct": 0
    }
  ],
  "mood_score": 49,
  "mood": "neutral",
  "mood_summary": "KOSPI +0.62% · KOSDAQ -0.77%"
}