{
  "fetched_at": "2026-07-14T01:23:19.426480+00:00",
  "kospi": {
    "price": 6871.22,
    "change_pct": 0.94,
    "label": "KOSPI"
  },
  "kosdaq": {
    "price": 783.97,
    "change_pct": -1.93,
    "label": "KOSDAQ"
  },
  "kospi200": {
    "price": 1095.37,
    "change_pct": 1.54,
    "label": "KPI200"
  },
  "watchlist": {
    "005930": {
      "price": 264750.0,
      "change_pct": 4.03,
      "name": "삼성전자",
      "code": "005930"
    },
    "000660": {
      "price": 1889000.0,
      "change_pct": 2.38,
      "name": "SK하이닉스",
      "code": "000660"
    },
    "373220": {
      "price": 324000.0,
      "change_pct": -1.37,
      "name": "LG에너지솔루션",
      "code": "373220"
    },
    "005380": {
      "price": 426000.0,
      "change_pct": -4.05,
      "name": "현대차",
      "code": "005380"
    },
    "035420": {
      "price": 186700.0,
      "change_pct": -0.69,
      "name": "NAVER",
      "code": "035420"
    },
    "035720": {
      "price": 34300.0,
      "change_pct": -1.29,
      "name": "카카오",
      "code": "035720"
    },
    "207940": {
      "price": 1365000.0,
      "change_pct": -2.5,
      "name": "삼성바이오로직스",
      "code": "207940"
    },
    "005490": {
      "price": 306000.0,
      "change_pct": -0.65,
      "name": "포스코홀딩스",
      "code": "005490"
    },
    "051910": {
      "price": 260500.0,
      "change_pct": 0.0,
      "name": "LG화학",
      "code": "051910"
    },
    "247540": {
      "price": 115300.0,
      "change_pct": -3.76,
      "name": "에코프로비엠",
      "code": "247540"
    }
  },
  "trending": [
    {
      "ticker": "000660",
      "name": "하이닉스",
      "mentions": 5,
      "surge_pct": 0
    },
    {
      "ticker": "005930",
      "name": "삼성전자",
      "mentions": 4,
      "surge_pct": 0
    },
    {
      "ticker": "041510",
      "name": "SM",
      "mentions": 4,
      "surge_pct": 0
    },
    {
      "ticker": "005380",
      "name": "현대차",
      "mentions": 3,
      "surge_pct": 0
    },
    {
      "ticker": "084180",
      "name": "수성웹툰",
      "mentions": 3,
      "surge_pct": 0
    },
    {
      "ticker": "000150",
      "name": "두산",
      "mentions": 2,
      "surge_pct": 0
    },
    {
      "ticker": "020560",
      "name": "아시아나항공",
      "mentions": 2,
      "surge_pct": 0
    },
    {
      "ticker": "900110",
      "name": "딥커머스",
      "mentions": 1,
      "surge_pct": 0
    },
    {
      "ticker": "191410",
      "name": "육일씨엔에쓰",
      "mentions": 1,
      "surge_pct": 0
    },
    {
      "ticker": "119830",
      "name": "아이텍",
      "mentions": 1,
      "surge_pct": 0
    }
  ],
  "mood_score": 43,
  "mood": "neutral",
  "mood_summary": "KOSPI +0.94% · KOSDAQ -1.93%"
}