{
  "fetched_at": "2026-05-05T19:50:44.335836+00:00",
  "sp500": {
    "price": 7262.54,
    "change_pct": 0.45,
    "label": "S&P 500"
  },
  "nasdaq": {
    "price": 25326.32,
    "change_pct": 0.84,
    "label": "Nasdaq"
  },
  "dow": {
    "price": 49314.2,
    "change_pct": -0.37,
    "label": "Dow"
  },
  "vix": {
    "price": 17.29,
    "change_pct": -5.47,
    "label": "VIX"
  },
  "btc": {
    "price": 81600.94,
    "change_pct": 1.99,
    "label": "BTC"
  },
  "watchlist": {
    "NVDA": {
      "price": 196.52,
      "change_pct": -0.99
    },
    "MRVL": {
      "price": 169,
      "change_pct": 3.26
    },
    "TSLA": {
      "price": 392.29,
      "change_pct": -0.06
    },
    "MSTR": {
      "price": 187.77,
      "change_pct": 2.16
    },
    "GOOGL": {
      "price": 387.63,
      "change_pct": 1.14
    },
    "AMD": {
      "price": 355.51,
      "change_pct": 4.09
    },
    "META": {
      "price": 605.88,
      "change_pct": -0.74
    },
    "MSFT": {
      "price": 411.95,
      "change_pct": -0.4
    },
    "AMZN": {
      "price": 273.96,
      "change_pct": 0.7
    },
    "AVGO": {
      "price": 428.5,
      "change_pct": 2.88
    }
  },
  "trending": [
    {
      "ticker": "NVDA",
      "mentions": 86,
      "surge_pct": 0
    },
    {
      "ticker": "GOOGL",
      "mentions": 21,
      "surge_pct": 0
    },
    {
      "ticker": "MSFT",
      "mentions": 16,
      "surge_pct": 0
    },
    {
      "ticker": "MU",
      "mentions": 11,
      "surge_pct": 0
    },
    {
      "ticker": "PLTR",
      "mentions": 11,
      "surge_pct": 0
    },
    {
      "ticker": "AAPL",
      "mentions": 11,
      "surge_pct": 0
    },
    {
      "ticker": "META",
      "mentions": 10,
      "surge_pct": 0
    },
    {
      "ticker": "AMZN",
      "mentions": 9,
      "surge_pct": 0
    },
    {
      "ticker": "AMD",
      "mentions": 6,
      "surge_pct": 0
    },
    {
      "ticker": "INTC",
      "mentions": 6,
      "surge_pct": 0
    }
  ],
  "mood_score": 60,
  "mood": "neutral",
  "mood_summary": "S&P +0.45% · Nasdaq +0.84%"
}