{
  "fetched_at": "2026-05-19T02:12:57.801627+00:00",
  "kospi": {
    "price": 7151.85,
    "change_pct": -4.85,
    "label": "KOSPI"
  },
  "kosdaq": {
    "price": 1064.63,
    "change_pct": -4.18,
    "label": "KOSDAQ"
  },
  "kospi200": {
    "price": 1112.98,
    "change_pct": -4.98,
    "label": "KPI200"
  },
  "watchlist": {
    "005930": {
      "price": 267000.0,
      "change_pct": -4.98,
      "name": "삼성전자",
      "code": "005930"
    },
    "000660": {
      "price": 1744000.0,
      "change_pct": -5.22,
      "name": "SK하이닉스",
      "code": "000660"
    },
    "373220": {
      "price": 390500.0,
      "change_pct": -4.29,
      "name": "LG에너지솔루션",
      "code": "373220"
    },
    "005380": {
      "price": 596500.0,
      "change_pct": -10.03,
      "name": "현대차",
      "code": "005380"
    },
    "035420": {
      "price": 195500.0,
      "change_pct": -2.25,
      "name": "NAVER",
      "code": "035420"
    },
    "035720": {
      "price": 41000.0,
      "change_pct": -3.42,
      "name": "카카오",
      "code": "035720"
    },
    "207940": {
      "price": 1349000.0,
      "change_pct": -2.67,
      "name": "삼성바이오로직스",
      "code": "207940"
    },
    "005490": {
      "price": 430500.0,
      "change_pct": -7.02,
      "name": "포스코홀딩스",
      "code": "005490"
    },
    "051910": {
      "price": 342500.0,
      "change_pct": -8.18,
      "name": "LG화학",
      "code": "051910"
    },
    "247540": {
      "price": 181700.0,
      "change_pct": -4.57,
      "name": "에코프로비엠",
      "code": "247540"
    }
  },
  "trending": [
    {
      "ticker": "005930",
      "name": "삼성전자",
      "mentions": 18,
      "surge_pct": 0
    },
    {
      "ticker": "000150",
      "name": "두산",
      "mentions": 6,
      "surge_pct": 0
    },
    {
      "ticker": "000660",
      "name": "SK하이닉스",
      "mentions": 4,
      "surge_pct": 0
    },
    {
      "ticker": "035720",
      "name": "카카오",
      "mentions": 3,
      "surge_pct": 0
    },
    {
      "ticker": "006740",
      "name": "블루산업개발",
      "mentions": 3,
      "surge_pct": 0
    },
    {
      "ticker": "035420",
      "name": "NAVER",
      "mentions": 2,
      "surge_pct": 0
    },
    {
      "ticker": "089230",
      "name": "THE E&M",
      "mentions": 2,
      "surge_pct": 0
    },
    {
      "ticker": "005380",
      "name": "현대차",
      "mentions": 2,
      "surge_pct": 0
    },
    {
      "ticker": "214420",
      "name": "토니모리",
      "mentions": 1,
      "surge_pct": 0
    },
    {
      "ticker": "052420",
      "name": "오성첨단소재",
      "mentions": 1,
      "surge_pct": 0
    }
  ],
  "mood_score": 0,
  "mood": "bearish",
  "mood_summary": "KOSPI -4.85% · KOSDAQ -4.18%"
}