{
  "fetched_at": "2026-04-29T13:22:39.681459+00:00",
  "sp500": {
    "price": 7138.8,
    "change_pct": -0.37,
    "label": "S&P 500"
  },
  "nasdaq": {
    "price": 24663.8,
    "change_pct": -0.7,
    "label": "Nasdaq"
  },
  "dow": {
    "price": 49141.93,
    "change_pct": -0.18,
    "label": "Dow"
  },
  "vix": {
    "price": 18.05,
    "change_pct": 1.23,
    "label": "VIX"
  },
  "btc": {
    "price": 77088.87,
    "change_pct": 1.24,
    "label": "BTC"
  },
  "watchlist": {
    "NVDA": {
      "price": 213.17,
      "change_pct": -1.59
    },
    "MRVL": {
      "price": 153.23,
      "change_pct": -3.15
    },
    "TSLA": {
      "price": 376.02,
      "change_pct": -0.7
    },
    "MSTR": {
      "price": 165.71,
      "change_pct": -2.06
    },
    "GOOGL": {
      "price": 349.78,
      "change_pct": -0.16
    },
    "AMD": {
      "price": 323.21,
      "change_pct": -3.41
    },
    "META": {
      "price": 671.34,
      "change_pct": -1.07
    },
    "MSFT": {
      "price": 429.25,
      "change_pct": 1.04
    },
    "AMZN": {
      "price": 259.7,
      "change_pct": -0.54
    },
    "AVGO": {
      "price": 399.83,
      "change_pct": -4.39
    }
  },
  "trending": [
    {
      "ticker": "NVDA",
      "mentions": 97,
      "surge_pct": 0
    },
    {
      "ticker": "GOOGL",
      "mentions": 24,
      "surge_pct": 0
    },
    {
      "ticker": "META",
      "mentions": 17,
      "surge_pct": 0
    },
    {
      "ticker": "MSFT",
      "mentions": 15,
      "surge_pct": 0
    },
    {
      "ticker": "MU",
      "mentions": 8,
      "surge_pct": 0
    },
    {
      "ticker": "TSLA",
      "mentions": 7,
      "surge_pct": 0
    },
    {
      "ticker": "MSTR",
      "mentions": 7,
      "surge_pct": 0
    },
    {
      "ticker": "AAPL",
      "mentions": 5,
      "surge_pct": 0
    },
    {
      "ticker": "AMZN",
      "mentions": 5,
      "surge_pct": 0
    },
    {
      "ticker": "INTC",
      "mentions": 4,
      "surge_pct": 0
    }
  ],
  "mood_score": 43,
  "mood": "neutral",
  "mood_summary": "S&P -0.37% · Nasdaq -0.70%"
}